{
  "allLanguages": ["en", "ja", "zh"],
  "defaultLanguage": "en",
  "currentPagesDir": "pages_",
  "finalPagesDir": "pages",
  "localesPath": "locales",
  "pages": {
    "*": ["_error", "common", "form"],
    "/": ["index", "papercups"],
    "/[spaceId]/activity": ["space"],
    "/[spaceId]/analytics": ["space"],
    "/[spaceId]/create": ["room", "space"],
    "/[spaceId]/edit": ["space"],
    "/[spaceId]/invite": ["space"],
    "/[spaceId]/invite/[inviteId]": ["auth", "space"],
    "/[spaceId]/leaderboard": ["space"],
    "/[spaceId]/members": ["space"],
    "/[spaceId]/room/[roomId]": ["space", "video"],
    "/[spaceId]/room/[roomId]/delete": ["room"],
    "/[spaceId]/room/[roomId]/edit": ["room"],
    "/[spaceId]/room/[roomId]/quit": ["room"],
    "/[spaceId]/room/[roomId]/settings": ["room"],
    "/[spaceId]/quit": ["space"],
    "/[spaceId]/settings": ["space"],
    "/[spaceId]": ["room", "space"],
    "/create": ["space"],
    "/dashboard": ["space"],
    "/login": ["auth", "papercups"],
    "/notifications": ["notifications"],
    "/privacy": ["auth", "papercups"],
    "/profile": ["profile"],
    "/settings": ["settings"],
    "/signup": ["auth", "papercups"],
    "/reset-password": ["auth", "papercups"],
    "/terms": ["auth", "papercups"]
  }
}
